{"wrapper":"div.index-sections","sections":{"linklist_xJPMXi":{"type":"linklist","custom_css":["a {font-size: 0.9em; font-family: lexend;}","section {display: none;}","@media (max-width: 768px) {section {display: flex; } ul.linklist__section--menu {justify-content: center; \/* enforce centering *\/ }}"],"name":"Link list","settings":{"menu":"quick-menu-mobile","color_scheme":"cs1","section_padding":"none"}},"slideshow_966bRM":{"type":"slideshow","blocks":{"image_pjK9Pb":{"type":"image","settings":{"image":"shopify:\/\/shop_images\/humure-banner-desktop-FR.jpg","mobile_image":"shopify:\/\/shop_images\/humure-banner-mobile-FR.jpg","overlay_color":"#000000","overlay_opacity":0,"text_align":"center","caption_horizontal":50,"caption_vertical":50,"heading":"","subheading":"","link":"https:\/\/zabcafe.com\/products\/rwanda-humure","button_text":"","text_color":"#ffffff","button_color":"#ffffff","button_background":"#000000","caption_background":"rgba(0,0,0,0)"}},"image_FqYBcM":{"type":"image","settings":{"image":"shopify:\/\/shop_images\/cafelimo-shopify-desktop-FR_b74b3d54-7a5b-46c4-9654-ddae52d68b31.jpg","mobile_image":"shopify:\/\/shop_images\/cafelimo-shopify-mobile-FR.jpg","overlay_color":"#000000","overlay_opacity":0,"text_align":"center","caption_horizontal":50,"caption_vertical":50,"heading":"","subheading":"","link":"https:\/\/zabcafe.com\/collections\/cafelimo","button_text":"","text_color":"#ffffff","button_color":"#ffffff","button_background":"#000000","caption_background":"rgba(0,0,0,0)"}},"image_fPPhDj":{"type":"image","settings":{"image":"shopify:\/\/shop_images\/urbania-x-zab-shopify-desktop-FR.jpg","mobile_image":"shopify:\/\/shop_images\/urbania-x-zab-shopify-mobile-FR.jpg","overlay_color":"#000000","overlay_opacity":0,"text_align":"center","caption_horizontal":50,"caption_vertical":50,"heading":"","subheading":"","link":"https:\/\/zabcafe.com\/collections\/cafes\/products\/urbania-x-zab","button_text":"","text_color":"#ffffff","button_color":"#ffffff","button_background":"#000000","caption_background":"rgba(0,0,0,0)"}},"image_9aKiki":{"type":"image","settings":{"image":"shopify:\/\/shop_images\/rudy-garcia-shopify-desktop-FR.jpg","mobile_image":"shopify:\/\/shop_images\/rudy-garcia-shopify-mobile-FR.jpg","overlay_color":"#000000","overlay_opacity":0,"text_align":"center","caption_horizontal":50,"caption_vertical":50,"heading":"","subheading":"","link":"https:\/\/zabcafe.com\/collections\/cafes\/products\/guatemala-rudy-garcia","button_text":"","text_color":"#ffffff","button_color":"#ffffff","button_background":"#000000","caption_background":"rgba(0,0,0,0)"}},"image_tbzVXA":{"type":"image","settings":{"image":"shopify:\/\/shop_images\/Banniere-abonnements.jpg","mobile_image":"shopify:\/\/shop_images\/Mobile-abonnements.jpg","overlay_color":"#000000","overlay_opacity":0,"text_align":"center","caption_horizontal":50,"caption_vertical":90,"heading":"","subheading":"","link":"shopify:\/\/pages\/abonnements-cafe","button_text":"Plus de détails ici","text_color":"#ffffff","button_color":"#ffffff","button_background":"#f38f1b","caption_background":"rgba(0,0,0,0)"}}},"block_order":["image_pjK9Pb","image_FqYBcM","image_fPPhDj","image_9aKiki","image_tbzVXA"],"disabled":true,"settings":{"enable_autoplay":true,"slider_speed":4,"display_wide":true,"slideshow_size":"natural","desktop_height":700,"mobile_height":600,"caption_below":true,"pager":"dots","slide_offset":false,"slide_heading_size":23,"subheading_size":14,"section_padding":"none"}},"slideshow_YyhFar":{"type":"slideshow","blocks":{"image_m8LkUK":{"type":"image","settings":{"image":"shopify:\/\/shop_images\/vente-808-2026-banner-desktop-FR.jpg","mobile_image":"shopify:\/\/shop_images\/vente-808-2026-banner-mobile-FR.jpg","overlay_color":"#000000","overlay_opacity":0,"text_align":"center","caption_horizontal":50,"caption_vertical":50,"heading":"","subheading":"","link":"https:\/\/zabcafe.com\/collections\/cafes","button_text":"","text_color":"#ffffff","button_color":"#ffffff","button_background":"#000000","caption_background":"rgba(0,0,0,0)"}},"image_7TgpnT":{"type":"image","settings":{"image":"shopify:\/\/shop_images\/allan-melgar-banner-desktop-FR.jpg","mobile_image":"shopify:\/\/shop_images\/allan-melgar-banner-mobile-FR.jpg","overlay_color":"#000000","overlay_opacity":0,"text_align":"center","caption_horizontal":50,"caption_vertical":50,"heading":"","subheading":"","link":"https:\/\/zabcafe.com\/products\/guatemala-allan-melgar","button_text":"","text_color":"#ffffff","button_color":"#ffffff","button_background":"#000000","caption_background":"rgba(0,0,0,0)"}},"image_qKg8dq":{"type":"image","settings":{"image":"shopify:\/\/shop_images\/foulard-go-zab-go-banner-desktop-FR.jpg","mobile_image":"shopify:\/\/shop_images\/foulard-go-zab-go-banner-mobile-FR.jpg","overlay_color":"#000000","overlay_opacity":0,"text_align":"center","caption_horizontal":50,"caption_vertical":50,"heading":"","subheading":"","link":"https:\/\/zabcafe.com\/products\/foulard-go-zab-go","button_text":"","text_color":"#ffffff","button_color":"#ffffff","button_background":"#000000","caption_background":"rgba(0,0,0,0)"}},"image_c3FXJy":{"type":"image","settings":{"image":"shopify:\/\/shop_images\/proyecto-berruecos-banner-desktop-FR.jpg","mobile_image":"shopify:\/\/shop_images\/proyecto-berruecos-banner-mobile-FR.jpg","overlay_color":"#000000","overlay_opacity":0,"text_align":"center","caption_horizontal":50,"caption_vertical":90,"heading":"","subheading":"","link":"https:\/\/zabcafe.com\/products\/colombie-proyecto-berruecos","button_text":"","text_color":"#ffffff","button_color":"#ffffff","button_background":"#f38f1b","caption_background":"rgba(0,0,0,0)"}}},"block_order":["image_m8LkUK","image_7TgpnT","image_qKg8dq","image_c3FXJy"],"settings":{"enable_autoplay":true,"slider_speed":4,"display_wide":true,"slideshow_size":"natural","desktop_height":700,"mobile_height":600,"caption_below":true,"pager":"dots","slide_offset":false,"slide_heading_size":23,"subheading_size":14,"section_padding":"none"}},"featured_collection_carousel_UJ9iWF":{"type":"featured-collection-carousel","disabled":true,"name":"Collection carousel","settings":{"collection":"cafelimo","grid":3,"limit":3,"ungroup_cells":false,"show_collection_image":false,"mobile_caption_top":false,"heading":"Featured collection","text":"<p>Display a featured collection alongside a paragraph of text and button.<\/p>","button":"Button","color_scheme":"none","section_padding":"both"}},"1629233737d5a73ae1":{"type":"collection-list","blocks":{"1629233737d5a73ae1-0":{"type":"featured_collection","settings":{"collection":"cafes"}},"featured_collection_Wwh6rF":{"type":"featured_collection","settings":{"collection":"cafelimo"}},"1629233737d5a73ae1-1":{"type":"featured_collection","settings":{"collection":"gear"}},"1629233737d5a73ae1-2":{"type":"featured_collection","settings":{"collection":"merch"}},"41ab1bab-1f8f-4a94-bf78-28eacbf45f3f":{"type":"featured_collection","settings":{"collection":"ateliers-cafe-zab"}}},"block_order":["1629233737d5a73ae1-0","featured_collection_Wwh6rF","1629233737d5a73ae1-1","1629233737d5a73ae1-2","41ab1bab-1f8f-4a94-bf78-28eacbf45f3f"],"disabled":true,"settings":{"title":"","collections_per_row":5,"mobile_single":false,"color_scheme":"cs1","section_padding":"top"}},"caroussel_v_zab01_JJCBQ9":{"type":"caroussel-vZab01","name":"Collection carousel vZAB","settings":{"collection":"nouveautes","grid":5,"limit":10,"ungroup_cells":false,"heading":"Nouveautés","title_alignment":"left","show_collection_link":false,"link_text":"Voir toute la collection","color_scheme":"none","section_padding":"both","custom_padding_top":20,"custom_padding_bottom":60,"enable_gradient_overlay":true,"gradient_top_color":"rgba(0,0,0,0)","gradient_top_height":100,"gradient_bottom_color":"#e1cdae","gradient_bottom_height":100,"enable_rounded_images":true,"image_border_radius":0,"enable_title_line":true,"title_line_width":150}},"caroussel_v_zab01_PKBLEh":{"type":"caroussel-vZab01","name":"Collection carousel vZAB","settings":{"collection":"cafes","grid":5,"limit":15,"ungroup_cells":false,"heading":"Nos cafés","title_alignment":"left","show_collection_link":true,"link_text":"Voir tous les cafés","color_scheme":"cs2","section_padding":"both","custom_padding_top":0,"custom_padding_bottom":60,"enable_gradient_overlay":false,"gradient_top_color":"#000000","gradient_top_height":100,"gradient_bottom_color":"#000000","gradient_bottom_height":100,"enable_rounded_images":true,"image_border_radius":0,"enable_title_line":true,"title_line_width":150}},"featured_collection_carousel_fbdHP3":{"type":"featured-collection-carousel","disabled":true,"name":"Collection carousel","settings":{"collection":"nouveautes","grid":4,"limit":8,"ungroup_cells":false,"show_collection_image":false,"mobile_caption_top":false,"heading":"Les nouveautés","text":"<p>Fraîchement arrivé!<br\/>Voici ce qu’il y a de neuf à la shop.<\/p>","button":"","color_scheme":"none","section_padding":"both"}},"featured_collection_carousel_LhHneF":{"type":"featured-collection-carousel","disabled":true,"name":"Collection carousel","settings":{"collection":"cafes","grid":4,"limit":10,"ungroup_cells":false,"show_collection_image":false,"mobile_caption_top":false,"heading":"Les cafés Zab","text":"<p>De classic à funky, Zab a ton back!<\/p>","button":"Voir tous les cafés","color_scheme":"cs2","section_padding":"top"}},"parallax_images_rwWFch":{"type":"parallax-images","blocks":{"image_aNqKDU":{"type":"image","settings":{"image":"shopify:\/\/shop_images\/fellow-aiden-2_copy.jpg","overlay_color":"#000000","overlay_opacity":20,"heading":"Équipements","subheading":"<p>Filtres, balances, bouilloires et bien plus!<\/p>","link":"shopify:\/\/collections\/gear","button_text":"Voir l'équipement","caption_position":"middle_center","text_color":"#efdab2","button_text_color":"#000000","button_color":"#efdab2"}},"image_8RUfTK":{"type":"image","settings":{"image":"shopify:\/\/shop_images\/Photoshoot_-_08.jpg","overlay_color":"#000000","overlay_opacity":24,"heading":"La Merch Zab","subheading":"","link":"shopify:\/\/collections\/merch","button_text":"Voir la merch","caption_position":"middle_center","text_color":"#f4e4bf","button_text_color":"#000000","button_color":"#efdab2"}},"image_iLGtRx":{"type":"image","settings":{"image":"shopify:\/\/shop_images\/4pack-cafelimo-back.jpg","overlay_color":"#000000","overlay_opacity":18,"heading":"Cafélimo","subheading":"<p>Nouveau 4 pack maintement disponible!<\/p>","link":"shopify:\/\/collections\/cafelimo","button_text":"Voir Cafélimo","caption_position":"middle_center","text_color":"#efdab2","button_text_color":"#000000","button_color":"#efdab2"}},"image_69LY3F":{"type":"image","settings":{"image":"shopify:\/\/shop_images\/photo-atelier.jpg","overlay_color":"#000000","overlay_opacity":20,"heading":"Ateliers","subheading":"<p>Perfectionnement pour tous!<\/p>","link":"shopify:\/\/collections\/ateliers-cafe-zab","button_text":"Voir les ateliers","caption_position":"middle_center","text_color":"#f4e4bf","button_text_color":"#000000","button_color":"#efdab2"}}},"block_order":["image_aNqKDU","image_8RUfTK","image_iLGtRx","image_69LY3F"],"custom_css":["h1,h2,h3,h4,h5,h6,p {text-shadow: 2px 2px 0 black; \/* X offset | Y offset | blur radius | color *\/}"],"name":"Parallax images","settings":{"section_height":800,"heading_size":50,"text_size":20,"section_height_mobile":400,"section_padding":"none"}},"featured_collection_carousel_tTLHhV":{"type":"featured-collection-carousel","name":"Collection carousel","settings":{"collection":"en-gros","grid":4,"limit":30,"ungroup_cells":false,"show_collection_image":false,"mobile_caption_top":true,"heading":"ZAB EN GROS","text":"<p>Rabais sur les achats en gros pour le bureau, le gym ou ton prochain party!<\/p>","button":"Voir les prix","color_scheme":"cs1","section_padding":"none"}},"featured_collection_carousel_DYqUTP":{"type":"featured-collection-carousel","disabled":true,"name":"Collection carousel","settings":{"collection":"gear","grid":4,"limit":30,"ungroup_cells":false,"show_collection_image":false,"mobile_caption_top":false,"heading":"Équipements","text":"<p>Balances, filtres, bouilloires et bien plus<\/p>","button":"Voir les équipements","color_scheme":"none","section_padding":"both"}},"video_YEmNLw":{"type":"video","disabled":true,"settings":{"heading":"","display_wide":false,"video_url":"https:\/\/youtu.be\/tobxA1I4yRI","description":"Describe the video for customers using screen readers","section_padding":"bottom"}},"34dd43eb-4e80-48f0-9b84-ead7909a25d8":{"type":"slideshow","blocks":{"template--19246785036597__34dd43eb-4e80-48f0-9b84-ead7909a25d8-1685107305a3d4587c-0":{"type":"image","settings":{"image":"shopify:\/\/shop_images\/banniere-wholesale-1800x800-01.jpg","overlay_color":"#000000","overlay_opacity":0,"text_align":"center","caption_horizontal":50,"caption_vertical":50,"heading":"Besoin d'aide pour votre ouverture de café?","subheading":"","link":"shopify:\/\/pages\/wholesale","button_text":"Plus d'informations ici","text_color":"#000000","button_color":"#ffffff","button_background":"#000000","caption_background":"#f4e4bf"}}},"block_order":["template--19246785036597__34dd43eb-4e80-48f0-9b84-ead7909a25d8-1685107305a3d4587c-0"],"settings":{"enable_autoplay":false,"slider_speed":5,"display_wide":true,"slideshow_size":"natural","desktop_height":900,"mobile_height":600,"caption_below":true,"pager":"dots","slide_offset":false,"slide_heading_size":24,"subheading_size":15,"section_padding":"none"}},"c16b4bb8-e5e8-458e-a957-1ce2f8aed9df":{"type":"custom-liquid","custom_css":[],"settings":{"liquid":"<center><h1 class=\"center a-center\">Torréfacteur de café de spécialité à Montréal<br> - Montreal specialty coffee roaster - <\/h1><\/center>","full_width":true,"section_padding":"both"}},"1753717006973b9b60":{"type":"apps","blocks":{"judge_me_reviews_medals_LJyFWa":{"type":"shopify:\/\/apps\/judge-me-reviews\/blocks\/medals\/61ccd3b1-a9f2-4160-9fe9-4fec8413e5d8","settings":{}}},"block_order":["judge_me_reviews_medals_LJyFWa"],"settings":{"full_width":false,"section_padding":"both"}},"17621688911d06c06b":{"type":"apps","blocks":{"essential_announcer_app_block_i49Xaq":{"type":"shopify:\/\/apps\/essential-announcer\/blocks\/app-block\/93b5429f-c8d6-4c33-ae14-250fd84f361b","settings":{"id":""}}},"block_order":["essential_announcer_app_block_i49Xaq"],"settings":{"full_width":false,"section_padding":"both"}}},"order":["linklist_xJPMXi","slideshow_966bRM","slideshow_YyhFar","featured_collection_carousel_UJ9iWF","1629233737d5a73ae1","caroussel_v_zab01_JJCBQ9","caroussel_v_zab01_PKBLEh","featured_collection_carousel_fbdHP3","featured_collection_carousel_LhHneF","parallax_images_rwWFch","featured_collection_carousel_tTLHhV","featured_collection_carousel_DYqUTP","video_YEmNLw","34dd43eb-4e80-48f0-9b84-ead7909a25d8","c16b4bb8-e5e8-458e-a957-1ce2f8aed9df","1753717006973b9b60","17621688911d06c06b"]}